pd_buddy_python-0.5.1.dist-info/DESCRIPTION.rst
pd_buddy_python-0.5.1.dist-info/METADATA
pd_buddy_python-0.5.1.dist-info/RECORD
pd_buddy_python-0.5.1.dist-info/WHEEL
pd_buddy_python-0.5.1.dist-info/metadata.json
pd_buddy_python-0.5.1.dist-info/top_level.txt
pdbuddy/__init__.py
pdbuddy/tools/__init__.py
pdbuddy/tools/test_sink.py
