Metadata-Version: 2.0
Name: pd-buddy-python
Version: 0.5.1
Summary: Python library for configuring PD Buddy Sink devices
Home-page: https://git.clayhobbs.com/pd-buddy/pd-buddy-python
Author: Clayton G. Hobbs
Author-email: clay@lakeserv.net
License: GPLv3+
Keywords: usb serial pd-buddy configuration
Platform: UNKNOWN
Classifier: Development Status :: 4 - Beta
Classifier: Intended Audience :: Developers
Classifier: License :: OSI Approved :: GNU General Public License v3 or later (GPLv3+)
Classifier: Operating System :: POSIX :: Linux
Classifier: Operating System :: MacOS :: MacOS X
Classifier: Operating System :: Microsoft :: Windows
Classifier: Programming Language :: Python
Classifier: Programming Language :: Python :: 2.7
Classifier: Programming Language :: Python :: 3.3
Classifier: Programming Language :: Python :: 3.4
Classifier: Programming Language :: Python :: 3.5
Classifier: Programming Language :: Python :: 3.6
Classifier: Topic :: Software Development :: User Interfaces
Requires-Dist: pyserial (<4,>=3)
Requires-Dist: aenum (>=2); python_version < "3.6"
